{
	"$schema": "https://json.schemastore.org/tsconfig",
	"display": "Default",
	"compilerOptions": {
		"esModuleInterop": true,
		"incremental": false,
		"isolatedModules": true,
		"lib": ["es2022", "DOM", "DOM.Iterable"],
		"module": "NodeNext",
		"moduleDetection": "force",
		"moduleResolution": "NodeNext",
		"noUncheckedIndexedAccess": true,
		"resolveJsonModule": true,
		"skipLibCheck": true,
		"strict": true,
		"target": "ES2022",
		"baseUrl": ".",
		"paths": {
			"@verifio/db": ["../../packages/db/src/*"],
			"@verifio/cache": ["../../packages/cache/src/*"],
			"@verifio/ui": ["../../packages/ui/src/*"],
			"@verifio/auth": ["../../packages/auth/src/*"],
			"@be/domain": ["../../apps/backend/domain/src/*"],
			"@be/workflow": ["../../apps/backend/workflow/src/*"],
			"@verifio/webhook": ["../../apps/backend/webhook/src/*"],
			"@verifio/audience": ["../../apps/backend/audience/src/*"],
			"@verifio/web": ["../../apps/frontend/web/src/*"],
			"@verifio/fe-dev": ["../../apps/frontend/dev/src/*"],
			"@verifio/be-mail": ["../../apps/backend/mail/src/*"]
		}
	}
}
